spass/__init__.py
spass/exceptions.py
spass/generators.py
spass/mapper.py
spass-1.2.1.dist-info/METADATA
spass-1.2.1.dist-info/RECORD
spass-1.2.1.dist-info/WHEEL
spass-1.2.1.dist-info/top_level.txt
