Metadata-Version: 2.1
Name: spass
Version: 1.2.1
Summary: Simple and Secure passphrases
Home-page: https://github.com/Tauag/spass
Author: Tauag
Author-email: dev.gavin.li@gmail.com
License: MIT
Project-URL: Source, https://github.com/Tauag/spass
Project-URL: Tracker, https://github.com/Tauag/spass/issues
Keywords: cryptography password passphrase secure
Platform: UNKNOWN
Classifier: Development Status :: 4 - Beta
Classifier: License :: OSI Approved :: MIT License
Classifier: Intended Audience :: Developers
Classifier: Programming Language :: Python :: 3
Requires-Python: >=3
